generate_invitation_codes.py
generate_invitation_codes-1.0.1.dist-info/METADATA
generate_invitation_codes-1.0.1.dist-info/WHEEL
generate_invitation_codes-1.0.1.dist-info/entry_points.txt
generate_invitation_codes-1.0.1.dist-info/top_level.txt
generate_invitation_codes-1.0.1.dist-info/RECORD
