Metadata-Version: 2.1
Name: generate-invitation-codes
Version: 1.0.1
